sauim_detector/__init__.py
sauim_detector/classifier.py
sauim_detector/cli.py
sauim_detector/loader.py
sauim_detector/models/ocsvm_sauim.joblib
sauim_detector-0.1.1.dist-info/METADATA
sauim_detector-0.1.1.dist-info/WHEEL
sauim_detector-0.1.1.dist-info/entry_points.txt
sauim_detector-0.1.1.dist-info/top_level.txt
sauim_detector-0.1.1.dist-info/RECORD
