Metadata-Version: 2.4
Name: sauim-detector
Version: 0.1.1
Summary: Bioacoustic processing and Pied tamarin (Saguinus bicolor) vocalization detector.
Author-email: Your Name <youremail@example.com>
License: MIT
Project-URL: Homepage, https://github.com/juancolonna/Sauim.git
Project-URL: Repository, https://github.com/juancolonna/Sauim.git
Requires-Python: >=3.9
Requires-Dist: joblib>=1.5.2
Requires-Dist: librosa>=0.11.0
Requires-Dist: numpy>=2.1.3
Requires-Dist: scipy>=1.15.3
Requires-Dist: soundfile>=0.13.1
Requires-Dist: tensorflow>=2.20.0
Requires-Dist: tensorflow-hub>=0.16.1
Requires-Dist: tqdm>=4.67.1
